vault_secrets/__init__.py
vault_secrets/__main__.py
vault_secrets-1.0.4.dist-info/METADATA
vault_secrets-1.0.4.dist-info/WHEEL
vault_secrets-1.0.4.dist-info/RECORD
